LICENSE
MANIFEST.in
README.md
setup.py
graphqlclient/__init__.py
graphqlclient/client.py
graphqlclient.egg-info/PKG-INFO
graphqlclient.egg-info/SOURCES.txt
graphqlclient.egg-info/dependency_links.txt
graphqlclient.egg-info/not-zip-safe
graphqlclient.egg-info/requires.txt
graphqlclient.egg-info/top_level.txt