Metadata-Version: 1.0
Name: graphqlclient
Version: 0.2.3
Summary: Simple GraphQL client for Python 2.7+
Home-page: https://github.com/prismagraphql/python-graphql-client
Author: prisma.io
Author-email: hello@prisma.io
License: MIT
Platform: UNKNOWN
